vaspc/__init__.py
vaspc/ase-convert.py
vaspc/ase-getINCAR.py
vaspc/ase-getpotcar.py
vaspc/main.py
vaspc/INCAR_temp/INCAR-opt
vaspc/POTCAR/POTCAR
vaspc/POTCAR/README.UPDATES
vaspc/POTCAR/data_base
vaspc/POTCAR/Ac/POTCAR
vaspc/POTCAR/Ac/PSCTR
vaspc/POTCAR/Ag/POTCAR
vaspc/POTCAR/Ag/PSCTR
vaspc/POTCAR/Ag_GW/POTCAR
vaspc/POTCAR/Ag_GW/PSCTR
vaspc/POTCAR/Ag_pv/POTCAR
vaspc/POTCAR/Ag_pv/PSCTR
vaspc/POTCAR/Ag_sv_GW/POTCAR
vaspc/POTCAR/Ag_sv_GW/PSCTR
vaspc/POTCAR/Al/POTCAR
vaspc/POTCAR/Al/PSCTR
vaspc/POTCAR/Al_GW/POTCAR
vaspc/POTCAR/Al_GW/PSCTR
vaspc/POTCAR/Al_sv_GW/POTCAR
vaspc/POTCAR/Al_sv_GW/PSCTR
vaspc/POTCAR/Am/POTCAR
vaspc/POTCAR/Am/PSCTR
vaspc/POTCAR/Ar/POTCAR
vaspc/POTCAR/Ar/PSCTR
vaspc/POTCAR/Ar_GW/POTCAR
vaspc/POTCAR/Ar_GW/PSCTR
vaspc/POTCAR/As/POTCAR
vaspc/POTCAR/As/PSCTR
vaspc/POTCAR/As_GW/POTCAR
vaspc/POTCAR/As_GW/PSCTR
vaspc/POTCAR/As_d/POTCAR
vaspc/POTCAR/As_d/PSCTR
vaspc/POTCAR/As_sv_GW/POTCAR
vaspc/POTCAR/As_sv_GW/PSCTR
vaspc/POTCAR/At/POTCAR
vaspc/POTCAR/At/PSCTR
vaspc/POTCAR/At_d_GW/POTCAR
vaspc/POTCAR/At_d_GW/PSCTR
vaspc/POTCAR/At_sv_GW/POTCAR
vaspc/POTCAR/At_sv_GW/PSCTR
vaspc/POTCAR/Au/POTCAR
vaspc/POTCAR/Au/PSCTR
vaspc/POTCAR/Au_GW/POTCAR
vaspc/POTCAR/Au_GW/PSCTR
vaspc/POTCAR/Au_sv_GW/POTCAR
vaspc/POTCAR/Au_sv_GW/PSCTR
vaspc/POTCAR/B/POTCAR
vaspc/POTCAR/B/PSCTR
vaspc/POTCAR/B_GW/POTCAR
vaspc/POTCAR/B_GW/PSCTR
vaspc/POTCAR/B_h/POTCAR
vaspc/POTCAR/B_h/PSCTR
vaspc/POTCAR/B_s/POTCAR
vaspc/POTCAR/B_s/PSCTR
vaspc/POTCAR/Ba_sv/POTCAR
vaspc/POTCAR/Ba_sv/PSCTR
vaspc/POTCAR/Ba_sv_GW/POTCAR
vaspc/POTCAR/Ba_sv_GW/PSCTR
vaspc/POTCAR/Be/POTCAR
vaspc/POTCAR/Be/PSCTR
vaspc/POTCAR/Be_GW/POTCAR
vaspc/POTCAR/Be_GW/PSCTR
vaspc/POTCAR/Be_sv/POTCAR
vaspc/POTCAR/Be_sv/PSCTR
vaspc/POTCAR/Be_sv_GW/POTCAR
vaspc/POTCAR/Be_sv_GW/PSCTR
vaspc/POTCAR/Bi/POTCAR
vaspc/POTCAR/Bi/PSCTR
vaspc/POTCAR/Bi_GW/POTCAR
vaspc/POTCAR/Bi_GW/PSCTR
vaspc/POTCAR/Bi_d/POTCAR
vaspc/POTCAR/Bi_d/PSCTR
vaspc/POTCAR/Bi_d_GW/POTCAR
vaspc/POTCAR/Bi_d_GW/PSCTR
vaspc/POTCAR/Bi_sv_GW/POTCAR
vaspc-0.1.3.dist-info/METADATA
vaspc-0.1.3.dist-info/WHEEL
vaspc-0.1.3.dist-info/entry_points.txt
vaspc-0.1.3.dist-info/top_level.txt
vaspc-0.1.3.dist-info/RECORD
