Metadata-Version: 2.2
Name: vaspc
Version: 0.1.3
Summary: A package to run multiple VASP-related Python scripts
Author-email: Your Name <your.email@example.com>
License: MIT
Requires-Python: >=3.6
Requires-Dist: ase
